README.rst
setup.py
nester_jeffwei/__init__.py
nester_jeffwei/nester_jeffwei.py
nester_jeffwei.egg-info/PKG-INFO
nester_jeffwei.egg-info/SOURCES.txt
nester_jeffwei.egg-info/dependency_links.txt
nester_jeffwei.egg-info/requires.txt
nester_jeffwei.egg-info/top_level.txt
nester_jeffwei.egg-info/zip-safe