Metadata-Version: 1.1
Name: nester-jeffwei
Version: 1.3.0
Summary: nester_jeffwei
Home-page: https://my.oschina.net/tianshl/blog
Author: jeff
Author-email: jeffwei@126.com
License: MIT
Keywords: nester_jeffwei
Platform: UNKNOWN
Classifier: License :: OSI Approved :: MIT License
Classifier: Programming Language :: Python
Classifier: Intended Audience :: Developers
Classifier: Operating System :: OS Independent
